{"meta":{"id":"1092","name":"[4th try] 18th tester) Webstore Freebie Placement A/B (5:5) (12/22~1/19)","type":"1","startPst":"2025-12-22T18:00:00.000Z","endPst":"2026-01-12T17:00:00.000Z","analysisEndPst":"2026-01-12","durationDays":21,"useEtl":false,"gameCode":"cvs","populationWeight":"[5,5]","dtRange":{"start":"2025-12-23","end":"2026-01-13","retEnd":"2026-01-15"}},"groups":[{"group_name":"Control","group_id":0,"n":482},{"group_name":"Treatment","group_id":1,"n":480}],"srmWarning":null,"controlName":"Control","allGroupNames":["Control","Treatment"],"groupSummary":{"Control":{"n":482,"preRevPerUser":335.67,"revPerUser":172.1,"payerRate":82.99,"retention":{"d1":84.02,"d3":83.2,"d7":80.29,"d14":76.35,"d21":0,"d30":0,"d60":0,"d90":0,"d120":0,"d150":0,"d180":0,"d360":0}},"Treatment":{"n":480,"preRevPerUser":302.66,"revPerUser":183.73,"payerRate":81.88,"retention":{"d1":82.08,"d3":83.96,"d7":82.5,"d14":77.5,"d21":0,"d30":0,"d60":0,"d90":0,"d120":0,"d150":0,"d180":0,"d360":0}}},"pairRevenue":{"Control|Treatment":{"a":{"n":482,"mean":172.1,"std":651.79,"nonZeroCount":400,"nonZeroMean":207.37,"nonZeroStd":710.5,"p50":68.4,"p75":204.73,"p90":400.41,"p99":1207.09},"b":{"n":480,"mean":183.73,"std":351.79,"nonZeroCount":393,"nonZeroMean":224.41,"nonZeroStd":376.92,"p50":89.9,"p75":249.96,"p90":597.92,"p99":1869.81},"allUserTest":{"diff":11.64,"ci_lo":-60.41,"ci_hi":74.44,"p":0.707,"sig":false,"probBetter":64.6},"payerRateTest":{"z":-0.453,"p":0.6503,"sig":false,"delta":-0.01113},"payerOnlyTest":{"diff":17.03,"ci_lo":-66.88,"ci_hi":91.4,"p":0.639,"sig":false,"probBetter":68},"cuperTest":{"diff":25.39,"ci_lo":-24.13,"ci_hi":69.67,"p":0.303,"sig":false,"probBetter":84.9},"cuperMeans":{"a":165.23,"b":190.62}}},"pairRetention":{"Control|Treatment":{"d1":{"a_rate":84.02,"b_rate":82.08,"test":{"z":-0.803,"p":0.4222,"sig":false,"delta":-0.01942}},"d3":{"a_rate":83.2,"b_rate":83.96,"test":{"z":0.32,"p":0.7493,"sig":false,"delta":0.00763}},"d7":{"a_rate":80.29,"b_rate":82.5,"test":{"z":0.88,"p":0.3786,"sig":false,"delta":0.0221}},"d14":{"a_rate":76.35,"b_rate":77.5,"test":{"z":0.424,"p":0.6717,"sig":false,"delta":0.01151}},"d21":{"a_rate":0,"b_rate":0,"test":{"z":0,"p":1,"sig":false,"delta":0}},"d30":{"a_rate":0,"b_rate":0,"test":{"z":0,"p":1,"sig":false,"delta":0}},"d60":{"a_rate":0,"b_rate":0,"test":{"z":0,"p":1,"sig":false,"delta":0}},"d90":{"a_rate":0,"b_rate":0,"test":{"z":0,"p":1,"sig":false,"delta":0}},"d120":{"a_rate":0,"b_rate":0,"test":{"z":0,"p":1,"sig":false,"delta":0}},"d150":{"a_rate":0,"b_rate":0,"test":{"z":0,"p":1,"sig":false,"delta":0}},"d180":{"a_rate":0,"b_rate":0,"test":{"z":0,"p":1,"sig":false,"delta":0}},"d360":{"a_rate":0,"b_rate":0,"test":{"z":0,"p":1,"sig":false,"delta":0}}}},"pairPrePeriod":{"Control|Treatment":{"revenue":{"a":335.67,"b":302.66,"test":{"t":-0.573,"p":0.5667,"sig":false,"delta":-33}},"payerRate":{"a":89.83,"b":89.58,"test":{"z":-0.128,"p":0.8982,"sig":false,"delta":-0.00251}},"revenuePerPayer":{"a":373.65,"b":337.86,"test":{"t":-0.562,"p":0.5743,"sig":false,"delta":-35.79}}}},"pairPostRollout":{"Control|Treatment":{"period":"2026-01-12 ~ 2026-03-13","a":{"n":482,"mean":522.81,"std":2786.23,"nonZeroCount":405,"nonZeroMean":622.21,"nonZeroStd":3029.97,"p50":154.84,"p75":425.17,"p90":961.08,"p99":7981.29},"b":{"n":480,"mean":396.15,"std":799.66,"nonZeroCount":409,"nonZeroMean":464.92,"nonZeroStd":847.76,"p50":199.98,"p75":499.99,"p90":1150.13,"p99":3351.85},"allUserTest":{"diff":-126.66,"ci_lo":-417.33,"ci_hi":93.95,"p":0.361,"sig":false,"probBetter":18.1},"payerRateTest":{"z":0.509,"p":0.611,"sig":false,"delta":0.01183}}},"segmentAnalysis":{"testMode":"OB Paid","segmentOrder":["Whale","Non-whale","Non-payer"],"segDist":{"Whale":{"Treatment":22,"Control":22},"Non-whale":{"Control":411,"Treatment":408},"Non-payer":{"Control":49,"Treatment":50}},"pairSegmentEffects":{"Control|Treatment":{"Whale":{"a":{"n":22,"mean":1435.9,"std":2710.77,"nonZeroCount":18,"nonZeroMean":1754.99,"nonZeroStd":2912.78,"p50":819.89,"p75":1189.89,"p90":4723.7,"p99":10666.67},"b":{"n":22,"mean":1047.21,"std":874.77,"nonZeroCount":21,"nonZeroMean":1097.08,"nonZeroStd":863.74,"p50":739.92,"p75":1584.93,"p90":2139.93,"p99":3406.75},"test":{"diff":-388.69,"ci_lo":-1712.15,"ci_hi":628.53,"p":0.563,"sig":false,"probBetter":28.1},"payerRateTest":{"z":1.425,"p":0.1541,"sig":false,"delta":0.13636}},"Non-whale":{"a":{"n":411,"mean":122.27,"std":175.63,"nonZeroCount":366,"nonZeroMean":137.31,"nonZeroStd":180.5,"p50":59.97,"p75":184.78,"p90":365.11,"p99":810.56},"b":{"n":408,"mean":157.89,"std":248.04,"nonZeroCount":356,"nonZeroMean":180.96,"nonZeroStd":257.59,"p50":82.44,"p75":225.81,"p90":446.92,"p99":1157.9},"test":{"diff":0.09,"ci_lo":-0.16,"ci_hi":0.35,"p":0.491,"sig":false,"probBetter":75.4},"payerRateTest":{"z":-0.795,"p":0.4264,"sig":false,"delta":-0.01796}},"Non-payer":{"a":{"n":49,"mean":22.56,"std":52.36,"nonZeroCount":16,"nonZeroMean":69.1,"nonZeroStd":73.08,"p50":32.48,"p75":99.99,"p90":199.99,"p99":208.46},"b":{"n":50,"mean":14.63,"std":35.69,"nonZeroCount":16,"nonZeroMean":45.73,"nonZeroStd":51.42,"p50":19.99,"p75":59.98,"p90":99.99,"p99":184.99},"test":{"diff":-0.11,"ci_lo":-0.83,"ci_hi":0.59,"p":0.73,"sig":false,"probBetter":36.5},"payerRateTest":{"z":-0.069,"p":0.9446,"sig":false,"delta":-0.00653}}}},"groupSegmentRevenue":{"Control":{"Whale":{"n":22,"mean":1435.9},"Non-whale":{"n":411,"mean":122.27},"Non-payer":{"n":49,"mean":22.56}},"Treatment":{"Whale":{"n":22,"mean":1047.21},"Non-whale":{"n":408,"mean":157.89},"Non-payer":{"n":50,"mean":14.63}}},"whaleThreshold":1234.84,"segmentStats":{"Whale":{"min":1234.84,"max":16139.48},"Non-whale":{"min":0.99,"max":1229.56}}},"cuperTheta":0.4168,"cuperRho":0.7112,"cuperVarianceReduction":50.6,"dailyRevRows":[{"group_name":"Control","segment":"Non-payer","day_num":0,"daily_revenue":210.96,"new_payers":3},{"group_name":"Control","segment":"Non-payer","day_num":1,"daily_revenue":19.99,"new_payers":1},{"group_name":"Control","segment":"Non-payer","day_num":2,"daily_revenue":29.99,"new_payers":1},{"group_name":"Control","segment":"Non-payer","day_num":3,"daily_revenue":19.98,"new_payers":0},{"group_name":"Control","segment":"Non-payer","day_num":4,"daily_revenue":254.97000000000003,"new_payers":3},{"group_name":"Control","segment":"Non-payer","day_num":5,"daily_revenue":69.99,"new_payers":1},{"group_name":"Control","segment":"Non-payer","day_num":6,"daily_revenue":4.99,"new_payers":1},{"group_name":"Control","segment":"Non-payer","day_num":7,"daily_revenue":19.99,"new_payers":1},{"group_name":"Control","segment":"Non-payer","day_num":8,"daily_revenue":39.98,"new_payers":0},{"group_name":"Control","segment":"Non-payer","day_num":9,"daily_revenue":69.97,"new_payers":0},{"group_name":"Control","segment":"Non-payer","day_num":10,"daily_revenue":4.99,"new_payers":1},{"group_name":"Control","segment":"Non-payer","day_num":11,"daily_revenue":129.98,"new_payers":1},{"group_name":"Control","segment":"Non-payer","day_num":12,"daily_revenue":9.98,"new_payers":2},{"group_name":"Control","segment":"Non-payer","day_num":13,"daily_revenue":49.959999999999994,"new_payers":0},{"group_name":"Control","segment":"Non-payer","day_num":16,"daily_revenue":4.99,"new_payers":0},{"group_name":"Control","segment":"Non-payer","day_num":17,"daily_revenue":59.980000000000004,"new_payers":0},{"group_name":"Control","segment":"Non-payer","day_num":19,"daily_revenue":104.97999999999999,"new_payers":1},{"group_name":"Control","segment":"Non-whale","day_num":0,"daily_revenue":4263.8299999999945,"new_payers":113},{"group_name":"Control","segment":"Non-whale","day_num":1,"daily_revenue":2138.3499999999995,"new_payers":48},{"group_name":"Control","segment":"Non-whale","day_num":2,"daily_revenue":3057.7499999999945,"new_payers":44},{"group_name":"Control","segment":"Non-whale","day_num":3,"daily_revenue":2571.069999999998,"new_payers":31},{"group_name":"Control","segment":"Non-whale","day_num":4,"daily_revenue":2787.849999999996,"new_payers":29},{"group_name":"Control","segment":"Non-whale","day_num":5,"daily_revenue":2504.0999999999995,"new_payers":17},{"group_name":"Control","segment":"Non-whale","day_num":6,"daily_revenue":1853.6300000000008,"new_payers":11},{"group_name":"Control","segment":"Non-whale","day_num":7,"daily_revenue":2078.48,"new_payers":14},{"group_name":"Control","segment":"Non-whale","day_num":8,"daily_revenue":2483.869999999999,"new_payers":8},{"group_name":"Control","segment":"Non-whale","day_num":9,"daily_revenue":2559.4500000000007,"new_payers":9},{"group_name":"Control","segment":"Non-whale","day_num":10,"daily_revenue":3173.2299999999996,"new_payers":7},{"group_name":"Control","segment":"Non-whale","day_num":11,"daily_revenue":1963.5800000000006,"new_payers":5},{"group_name":"Control","segment":"Non-whale","day_num":12,"daily_revenue":2332.4099999999994,"new_payers":7},{"group_name":"Control","segment":"Non-whale","day_num":13,"daily_revenue":2305.35,"new_payers":5},{"group_name":"Control","segment":"Non-whale","day_num":14,"daily_revenue":3291.590000000001,"new_payers":6},{"group_name":"Control","segment":"Non-whale","day_num":15,"daily_revenue":1586.7100000000005,"new_payers":4},{"group_name":"Control","segment":"Non-whale","day_num":16,"daily_revenue":1966.6000000000006,"new_payers":2},{"group_name":"Control","segment":"Non-whale","day_num":17,"daily_revenue":1891.0100000000007,"new_payers":2},{"group_name":"Control","segment":"Non-whale","day_num":18,"daily_revenue":1682.450000000001,"new_payers":1},{"group_name":"Control","segment":"Non-whale","day_num":19,"daily_revenue":1512.8800000000003,"new_payers":1},{"group_name":"Control","segment":"Non-whale","day_num":20,"daily_revenue":1731.6300000000008,"new_payers":1},{"group_name":"Control","segment":"Non-whale","day_num":21,"daily_revenue":518.61,"new_payers":1},{"group_name":"Control","segment":"Whale","day_num":0,"daily_revenue":1234.8000000000002,"new_payers":9},{"group_name":"Control","segment":"Whale","day_num":1,"daily_revenue":1499.71,"new_payers":2},{"group_name":"Control","segment":"Whale","day_num":2,"daily_revenue":1410.75,"new_payers":0},{"group_name":"Control","segment":"Whale","day_num":3,"daily_revenue":981.8,"new_payers":0},{"group_name":"Control","segment":"Whale","day_num":4,"daily_revenue":1429.66,"new_payers":2},{"group_name":"Control","segment":"Whale","day_num":5,"daily_revenue":1414.6100000000001,"new_payers":0},{"group_name":"Control","segment":"Whale","day_num":6,"daily_revenue":1489.67,"new_payers":1},{"group_name":"Control","segment":"Whale","day_num":7,"daily_revenue":734.75,"new_payers":1},{"group_name":"Control","segment":"Whale","day_num":8,"daily_revenue":562.88,"new_payers":0},{"group_name":"Control","segment":"Whale","day_num":9,"daily_revenue":1239.92,"new_payers":0},{"group_name":"Control","segment":"Whale","day_num":10,"daily_revenue":1824.7300000000002,"new_payers":0},{"group_name":"Control","segment":"Whale","day_num":11,"daily_revenue":798.64,"new_payers":0},{"group_name":"Control","segment":"Whale","day_num":12,"daily_revenue":1682.69,"new_payers":0},{"group_name":"Control","segment":"Whale","day_num":13,"daily_revenue":844.74,"new_payers":0},{"group_name":"Control","segment":"Whale","day_num":14,"daily_revenue":2044.7400000000002,"new_payers":0},{"group_name":"Control","segment":"Whale","day_num":15,"daily_revenue":2261.44,"new_payers":3},{"group_name":"Control","segment":"Whale","day_num":16,"daily_revenue":1970.65,"new_payers":0},{"group_name":"Control","segment":"Whale","day_num":17,"daily_revenue":1737.65,"new_payers":0},{"group_name":"Control","segment":"Whale","day_num":18,"daily_revenue":1822.7400000000002,"new_payers":0},{"group_name":"Control","segment":"Whale","day_num":19,"daily_revenue":1569.5900000000001,"new_payers":0},{"group_name":"Control","segment":"Whale","day_num":20,"daily_revenue":2713.6600000000003,"new_payers":0},{"group_name":"Control","segment":"Whale","day_num":21,"daily_revenue":319.95,"new_payers":0},{"group_name":"Treatment","segment":"Non-payer","day_num":0,"daily_revenue":54.97,"new_payers":3},{"group_name":"Treatment","segment":"Non-payer","day_num":1,"daily_revenue":169.95,"new_payers":3},{"group_name":"Treatment","segment":"Non-payer","day_num":2,"daily_revenue":29.99,"new_payers":1},{"group_name":"Treatment","segment":"Non-payer","day_num":3,"daily_revenue":219.98000000000002,"new_payers":1},{"group_name":"Treatment","segment":"Non-payer","day_num":6,"daily_revenue":9.99,"new_payers":0},{"group_name":"Treatment","segment":"Non-payer","day_num":7,"daily_revenue":9.99,"new_payers":1},{"group_name":"Treatment","segment":"Non-payer","day_num":8,"daily_revenue":4.99,"new_payers":1},{"group_name":"Treatment","segment":"Non-payer","day_num":10,"daily_revenue":19.99,"new_payers":1},{"group_name":"Treatment","segment":"Non-payer","day_num":11,"daily_revenue":121.96,"new_payers":3},{"group_name":"Treatment","segment":"Non-payer","day_num":16,"daily_revenue":4.99,"new_payers":0},{"group_name":"Treatment","segment":"Non-payer","day_num":17,"daily_revenue":39.98,"new_payers":1},{"group_name":"Treatment","segment":"Non-payer","day_num":18,"daily_revenue":9.99,"new_payers":0},{"group_name":"Treatment","segment":"Non-payer","day_num":19,"daily_revenue":14.98,"new_payers":0},{"group_name":"Treatment","segment":"Non-payer","day_num":20,"daily_revenue":19.99,"new_payers":1},{"group_name":"Treatment","segment":"Non-whale","day_num":0,"daily_revenue":2905.1399999999962,"new_payers":93},{"group_name":"Treatment","segment":"Non-whale","day_num":1,"daily_revenue":2820.599999999997,"new_payers":61},{"group_name":"Treatment","segment":"Non-whale","day_num":2,"daily_revenue":3110.889999999996,"new_payers":40},{"group_name":"Treatment","segment":"Non-whale","day_num":3,"daily_revenue":3221.759999999995,"new_payers":30},{"group_name":"Treatment","segment":"Non-whale","day_num":4,"daily_revenue":3556.719999999996,"new_payers":25},{"group_name":"Treatment","segment":"Non-whale","day_num":5,"daily_revenue":3232.7099999999973,"new_payers":16},{"group_name":"Treatment","segment":"Non-whale","day_num":6,"daily_revenue":4004.6199999999967,"new_payers":24},{"group_name":"Treatment","segment":"Non-whale","day_num":7,"daily_revenue":3677.4399999999973,"new_payers":15},{"group_name":"Treatment","segment":"Non-whale","day_num":8,"daily_revenue":3308.3599999999974,"new_payers":8},{"group_name":"Treatment","segment":"Non-whale","day_num":9,"daily_revenue":2870.7699999999995,"new_payers":4},{"group_name":"Treatment","segment":"Non-whale","day_num":10,"daily_revenue":3450.449999999999,"new_payers":5},{"group_name":"Treatment","segment":"Non-whale","day_num":11,"daily_revenue":3317.9499999999985,"new_payers":9},{"group_name":"Treatment","segment":"Non-whale","day_num":12,"daily_revenue":2024.0700000000004,"new_payers":2},{"group_name":"Treatment","segment":"Non-whale","day_num":13,"daily_revenue":3114.989999999999,"new_payers":6},{"group_name":"Treatment","segment":"Non-whale","day_num":14,"daily_revenue":3809.9099999999994,"new_payers":4},{"group_name":"Treatment","segment":"Non-whale","day_num":15,"daily_revenue":3155.7899999999995,"new_payers":2},{"group_name":"Treatment","segment":"Non-whale","day_num":16,"daily_revenue":2525.1200000000003,"new_payers":2},{"group_name":"Treatment","segment":"Non-whale","day_num":17,"daily_revenue":2699.8999999999983,"new_payers":1},{"group_name":"Treatment","segment":"Non-whale","day_num":18,"daily_revenue":2296.8399999999992,"new_payers":6},{"group_name":"Treatment","segment":"Non-whale","day_num":19,"daily_revenue":2284.279999999999,"new_payers":2},{"group_name":"Treatment","segment":"Non-whale","day_num":20,"daily_revenue":1902.48,"new_payers":1},{"group_name":"Treatment","segment":"Non-whale","day_num":21,"daily_revenue":1130.1900000000003,"new_payers":0},{"group_name":"Treatment","segment":"Whale","day_num":0,"daily_revenue":954.7,"new_payers":9},{"group_name":"Treatment","segment":"Whale","day_num":1,"daily_revenue":304.90000000000003,"new_payers":2},{"group_name":"Treatment","segment":"Whale","day_num":2,"daily_revenue":826.6600000000001,"new_payers":7},{"group_name":"Treatment","segment":"Whale","day_num":3,"daily_revenue":1833.66,"new_payers":1},{"group_name":"Treatment","segment":"Whale","day_num":4,"daily_revenue":2867.7,"new_payers":1},{"group_name":"Treatment","segment":"Whale","day_num":5,"daily_revenue":824.78,"new_payers":0},{"group_name":"Treatment","segment":"Whale","day_num":6,"daily_revenue":1018.7400000000001,"new_payers":0},{"group_name":"Treatment","segment":"Whale","day_num":7,"daily_revenue":1902.67,"new_payers":0},{"group_name":"Treatment","segment":"Whale","day_num":8,"daily_revenue":1939.8700000000001,"new_payers":0},{"group_name":"Treatment","segment":"Whale","day_num":9,"daily_revenue":1259.91,"new_payers":0},{"group_name":"Treatment","segment":"Whale","day_num":10,"daily_revenue":2754.8100000000004,"new_payers":1},{"group_name":"Treatment","segment":"Whale","day_num":11,"daily_revenue":509.93,"new_payers":0},{"group_name":"Treatment","segment":"Whale","day_num":12,"daily_revenue":799.74,"new_payers":0},{"group_name":"Treatment","segment":"Whale","day_num":13,"daily_revenue":144.82,"new_payers":0},{"group_name":"Treatment","segment":"Whale","day_num":14,"daily_revenue":286.82000000000005,"new_payers":0},{"group_name":"Treatment","segment":"Whale","day_num":15,"daily_revenue":1334.8200000000002,"new_payers":0},{"group_name":"Treatment","segment":"Whale","day_num":16,"daily_revenue":624.8800000000001,"new_payers":0},{"group_name":"Treatment","segment":"Whale","day_num":17,"daily_revenue":915.54,"new_payers":0},{"group_name":"Treatment","segment":"Whale","day_num":18,"daily_revenue":1381.8400000000001,"new_payers":0},{"group_name":"Treatment","segment":"Whale","day_num":19,"daily_revenue":500.98,"new_payers":0},{"group_name":"Treatment","segment":"Whale","day_num":20,"daily_revenue":30.930000000000003,"new_payers":0},{"group_name":"Treatment","segment":"Whale","day_num":21,"daily_revenue":19.99,"new_payers":0}],"dailyPreRevRows":[{"group_name":"Control","day_num":-30,"daily_revenue":4800.209999999991,"new_payers":127,"n_users":482},{"group_name":"Control","day_num":-29,"daily_revenue":5211.959999999988,"new_payers":62,"n_users":482},{"group_name":"Control","day_num":-28,"daily_revenue":5670.099999999991,"new_payers":51,"n_users":482},{"group_name":"Control","day_num":-27,"daily_revenue":5704.1599999999935,"new_payers":28,"n_users":482},{"group_name":"Control","day_num":-26,"daily_revenue":6713.1199999999935,"new_payers":27,"n_users":482},{"group_name":"Control","day_num":-25,"daily_revenue":4805.569999999995,"new_payers":20,"n_users":482},{"group_name":"Control","day_num":-24,"daily_revenue":4276.2199999999975,"new_payers":16,"n_users":482},{"group_name":"Control","day_num":-23,"daily_revenue":6177.239999999998,"new_payers":16,"n_users":482},{"group_name":"Control","day_num":-22,"daily_revenue":6140.949999999998,"new_payers":8,"n_users":482},{"group_name":"Control","day_num":-21,"daily_revenue":4735.649999999999,"new_payers":12,"n_users":482},{"group_name":"Control","day_num":-20,"daily_revenue":5987.119999999998,"new_payers":7,"n_users":482},{"group_name":"Control","day_num":-19,"daily_revenue":7266.439999999995,"new_payers":11,"n_users":482},{"group_name":"Control","day_num":-18,"daily_revenue":3688.220000000001,"new_payers":6,"n_users":482},{"group_name":"Control","day_num":-17,"daily_revenue":5254.389999999999,"new_payers":5,"n_users":482},{"group_name":"Control","day_num":-16,"daily_revenue":6197.39,"new_payers":2,"n_users":482},{"group_name":"Control","day_num":-15,"daily_revenue":7256.309999999997,"new_payers":7,"n_users":482},{"group_name":"Control","day_num":-14,"daily_revenue":4461.65,"new_payers":5,"n_users":482},{"group_name":"Control","day_num":-13,"daily_revenue":5679.350000000002,"new_payers":3,"n_users":482},{"group_name":"Control","day_num":-12,"daily_revenue":9186.129999999997,"new_payers":0,"n_users":482},{"group_name":"Control","day_num":-11,"daily_revenue":7788.150000000001,"new_payers":5,"n_users":482},{"group_name":"Control","day_num":-10,"daily_revenue":5140.5,"new_payers":2,"n_users":482},{"group_name":"Control","day_num":-9,"daily_revenue":4360.400000000001,"new_payers":3,"n_users":482},{"group_name":"Control","day_num":-8,"daily_revenue":4706.61,"new_payers":3,"n_users":482},{"group_name":"Control","day_num":-7,"daily_revenue":6625.91,"new_payers":0,"n_users":482},{"group_name":"Control","day_num":-6,"daily_revenue":3171.3100000000004,"new_payers":0,"n_users":482},{"group_name":"Control","day_num":-5,"daily_revenue":4574.79,"new_payers":3,"n_users":482},{"group_name":"Control","day_num":-4,"daily_revenue":3832.7199999999993,"new_payers":3,"n_users":482},{"group_name":"Control","day_num":-3,"daily_revenue":4105.72,"new_payers":0,"n_users":482},{"group_name":"Control","day_num":-2,"daily_revenue":4410.580000000001,"new_payers":0,"n_users":482},{"group_name":"Control","day_num":-1,"daily_revenue":3861.9800000000005,"new_payers":1,"n_users":482},{"group_name":"Treatment","day_num":-30,"daily_revenue":5256.399999999987,"new_payers":131,"n_users":480},{"group_name":"Treatment","day_num":-29,"daily_revenue":4458.579999999989,"new_payers":58,"n_users":480},{"group_name":"Treatment","day_num":-28,"daily_revenue":7288.959999999986,"new_payers":64,"n_users":480},{"group_name":"Treatment","day_num":-27,"daily_revenue":4431.609999999994,"new_payers":30,"n_users":480},{"group_name":"Treatment","day_num":-26,"daily_revenue":3329.5099999999957,"new_payers":24,"n_users":480},{"group_name":"Treatment","day_num":-25,"daily_revenue":5494.239999999995,"new_payers":25,"n_users":480},{"group_name":"Treatment","day_num":-24,"daily_revenue":5915.609999999998,"new_payers":16,"n_users":480},{"group_name":"Treatment","day_num":-23,"daily_revenue":6757.89,"new_payers":12,"n_users":480},{"group_name":"Treatment","day_num":-22,"daily_revenue":4614.979999999999,"new_payers":10,"n_users":480},{"group_name":"Treatment","day_num":-21,"daily_revenue":5144.189999999999,"new_payers":4,"n_users":480},{"group_name":"Treatment","day_num":-20,"daily_revenue":5101.64,"new_payers":6,"n_users":480},{"group_name":"Treatment","day_num":-19,"daily_revenue":5467.3499999999985,"new_payers":5,"n_users":480},{"group_name":"Treatment","day_num":-18,"daily_revenue":4319.380000000001,"new_payers":2,"n_users":480},{"group_name":"Treatment","day_num":-17,"daily_revenue":6100.59,"new_payers":4,"n_users":480},{"group_name":"Treatment","day_num":-16,"daily_revenue":6366.49,"new_payers":6,"n_users":480},{"group_name":"Treatment","day_num":-15,"daily_revenue":4429.539999999999,"new_payers":7,"n_users":480},{"group_name":"Treatment","day_num":-14,"daily_revenue":2771.0099999999998,"new_payers":2,"n_users":480},{"group_name":"Treatment","day_num":-13,"daily_revenue":3892.71,"new_payers":2,"n_users":480},{"group_name":"Treatment","day_num":-12,"daily_revenue":3635.6300000000006,"new_payers":3,"n_users":480},{"group_name":"Treatment","day_num":-11,"daily_revenue":4453.530000000001,"new_payers":3,"n_users":480},{"group_name":"Treatment","day_num":-10,"daily_revenue":3863.51,"new_payers":3,"n_users":480},{"group_name":"Treatment","day_num":-9,"daily_revenue":6245.150000000001,"new_payers":3,"n_users":480},{"group_name":"Treatment","day_num":-8,"daily_revenue":5756.270000000001,"new_payers":1,"n_users":480},{"group_name":"Treatment","day_num":-7,"daily_revenue":3221.9700000000003,"new_payers":1,"n_users":480},{"group_name":"Treatment","day_num":-6,"daily_revenue":3011.78,"new_payers":0,"n_users":480},{"group_name":"Treatment","day_num":-5,"daily_revenue":4767.64,"new_payers":0,"n_users":480},{"group_name":"Treatment","day_num":-4,"daily_revenue":4040.790000000001,"new_payers":1,"n_users":480},{"group_name":"Treatment","day_num":-3,"daily_revenue":6097.48,"new_payers":4,"n_users":480},{"group_name":"Treatment","day_num":-2,"daily_revenue":3719.5199999999995,"new_payers":1,"n_users":480},{"group_name":"Treatment","day_num":-1,"daily_revenue":5325.24,"new_payers":2,"n_users":480}],"dailyProductRows":[],"productAnalysis":{"allProductTypes":[],"pairProductEffects":{"Control|Treatment":{}}}}